verilog/Project7_Shift_register/src_latch/RX_shift_reg.v
module RX_shift_reg #(parameter W=32)(
    input N,
    input clk,reset,shift,
    output reg [W-1:0]D_out
);

    always @(posedge clk or posedge reset)begin
        if(reset)begin
            D_out<=0;
        end 
        else if(shift)begin
            D_out<={N,D_out[W-1:1]};
        end
    end
endmodule

verilog/Project7_Shift_register/src_latch/TX_shift_reg.v
module TX_shift_reg #(parameter W=32)(
    input [W-1:0]D_in,
    input clk,reset,load,shift,
    output N,fin
);
    reg [5:0]count;
    reg [W-1:0]Q_a;
    assign N=Q_a[0];
    assign fin=(count==32)?1'b1:1'b0;

    always @(posedge clk or posedge reset) begin
        if(reset)begin
            Q_a<=0;
        end
        else if(load)begin
            Q_a<=D_in;
        end
        else if(shift)begin
            Q_a<={1'b0,Q_a[W-1:1]};
        end
    end
    always @(posedge clk or posedge reset) begin
        if(reset)begin
            count<=0;
        end
        else if(load)begin
            count<=0;
        end
        else if(shift)begin
            count<=count+1;
        end
    end
    
endmodule

verilog/Project7_Shift_register/src_latch/Top_register.v
module Top_register #(parameter W=32)(
    input clk,reset,shift,load,
    input [W-1:0] D_in,
    output [W-1:0] D_out,
    output fin
);
    wire N;

    TX_shift_reg #(.W(W))reg0(
        .clk(clk),.reset(reset),.shift(shift),.load(load),
        .D_in(D_in),.N(N),.fin(fin)
    );

    RX_shift_reg #(.W(W))reg1(
        .clk(clk),.reset(reset),.shift(shift),
        .D_out(D_out),.N(N)
    );
endmodule

verilog/Project7_Shift_register/tb/shift_reg_tb.v
`timescale 1ns/1ps
module shift_reg_tb #(parameter W=32);
    reg [W-1:0]D_in;
    reg clk,load,reset,shift;
    wire [W-1:0]D_out;
    wire fin;

    always #5 clk=~clk;

    Top_register #(.W(32))uut0(
        .D_in(D_in),
        .clk(clk),
        .reset(reset),
        .load(load),
        .shift(shift),
        .D_out(D_out),
        .fin(fin)
    );

    initial begin
        $dumpfile("Shift_register.vcd");
        $dumpvars(0,shift_reg_tb);
    end

    integer i;
    initial begin
        clk=0; reset=1; load=0; shift=0;
        D_in = 32'd0;
        #15;
        reset=0;
        D_in=32'hA5A5_F0F0;
        
        @(posedge clk);
        load=1;
        
        @(posedge clk);
        load=0;
        shift=1;

        wait(fin==1'b1);

        @(posedge clk);
        shift=0;
        #20;
        $finish;

    end
endmodule

Shift_register.vcd
$date
	Fri Jun 19 09:59:01 2026
$end
$version
	Icarus Verilog
$end
$timescale
	1ps
$end
$scope module shift_reg_tb $end
$var wire 1 ! fin $end
$var wire 32 " D_out [31:0] $end
$var reg 32 # D_in [31:0] $end
$var reg 1 $ clk $end
$var reg 1 % load $end
$var reg 1 & reset $end
$var reg 1 ' shift $end
$scope module uut0 $end
$var wire 32 ( D_in [31:0] $end
$var wire 1 $ clk $end
$var wire 1 % load $end
$var wire 1 & reset $end
$var wire 1 ' shift $end
$var wire 1 ! fin $end
$var wire 1 ) N $end
$var wire 32 * D_out [31:0] $end
$scope module reg0 $end
$var wire 32 + D_in [31:0] $end
$var wire 1 $ clk $end
$var wire 1 % load $end
$var wire 1 & reset $end
$var wire 1 ' shift $end
$var wire 1 ! fin $end
$var wire 1 ) N $end
$var reg 32 , Q_a [31:0] $end
$var reg 6 - count [5:0] $end
$upscope $end
$scope module reg1 $end
$var wire 1 ) N $end
$var wire 1 $ clk $end
$var wire 1 & reset $end
$var wire 1 ' shift $end
$var reg 32 . D_out [31:0] $end
$upscope $end
$upscope $end
$upscope $end
$enddefinitions $end
#0
$dumpvars
b0 .
b0 -
b0 ,
b0 +
b0 *
0)
b0 (
0'
1&
0%
0$
b0 #
b0 "
0!
$end
#5000
1$
#10000
0$
#15000
b10100101101001011111000011110000 ,
1%
1$
b10100101101001011111000011110000 #
b10100101101001011111000011110000 (
b10100101101001011111000011110000 +
0&
#20000
0$
#25000
b1 -
b1010010110100101111100001111000 ,
1'
0%
1$
#30000
0$
#35000
b101001011010010111110000111100 ,
b10 -
1$
#40000
0$
#45000
b11 -
b10100101101001011111000011110 ,
1$
#50000
0$
#55000
1)
b1010010110100101111100001111 ,
b100 -
1$
#60000
0$
#65000
b10000000000000000000000000000000 "
b10000000000000000000000000000000 *
b10000000000000000000000000000000 .
b101 -
b101001011010010111110000111 ,
1$
#70000
0$
#75000
b10100101101001011111000011 ,
b110 -
b11000000000000000000000000000000 "
b11000000000000000000000000000000 *
b11000000000000000000000000000000 .
1$
#80000
0$
#85000
b11100000000000000000000000000000 "
b11100000000000000000000000000000 *
b11100000000000000000000000000000 .
b111 -
b1010010110100101111100001 ,
1$
#90000
0$
#95000
0)
b101001011010010111110000 ,
b1000 -
b11110000000000000000000000000000 "
b11110000000000000000000000000000 *
b11110000000000000000000000000000 .
1$
#100000
0$
#105000
b1111000000000000000000000000000 "
b1111000000000000000000000000000 *
b1111000000000000000000000000000 .
b1001 -
b10100101101001011111000 ,
1$
#110000
0$
#115000
b1010010110100101111100 ,
b1010 -
b111100000000000000000000000000 "
b111100000000000000000000000000 *
b111100000000000000000000000000 .
1$
#120000
0$
#125000
b11110000000000000000000000000 "
b11110000000000000000000000000 *
b11110000000000000000000000000 .
b1011 -
b101001011010010111110 ,
1$
#130000
0$
#135000
1)
b10100101101001011111 ,
b1100 -
b1111000000000000000000000000 "
b1111000000000000000000000000 *
b1111000000000000000000000000 .
1$
#140000
0$
#145000
b10000111100000000000000000000000 "
b10000111100000000000000000000000 *
b10000111100000000000000000000000 .
b1101 -
b1010010110100101111 ,
1$
#150000
0$
#155000
b101001011010010111 ,
b1110 -
b11000011110000000000000000000000 "
b11000011110000000000000000000000 *
b11000011110000000000000000000000 .
1$
#160000
0$
#165000
b11100001111000000000000000000000 "
b11100001111000000000000000000000 *
b11100001111000000000000000000000 .
b1111 -
b10100101101001011 ,
1$
#170000
0$
#175000
b1010010110100101 ,
b10000 -
b11110000111100000000000000000000 "
b11110000111100000000000000000000 *
b11110000111100000000000000000000 .
1$
#180000
0$
#185000
0)
b11111000011110000000000000000000 "
b11111000011110000000000000000000 *
b11111000011110000000000000000000 .
b10001 -
b101001011010010 ,
1$
#190000
0$
#195000
1)
b10100101101001 ,
b10010 -
b1111100001111000000000000000000 "
b1111100001111000000000000000000 *
b1111100001111000000000000000000 .
1$
#200000
0$
#205000
0)
b10111110000111100000000000000000 "
b10111110000111100000000000000000 *
b10111110000111100000000000000000 .
b10011 -
b1010010110100 ,
1$
#210000
0$
#215000
b101001011010 ,
b10100 -
b1011111000011110000000000000000 "
b1011111000011110000000000000000 *
b1011111000011110000000000000000 .
1$
#220000
0$
#225000
1)
b101111100001111000000000000000 "
b101111100001111000000000000000 *
b101111100001111000000000000000 .
b10101 -
b10100101101 ,
1$
#230000
0$
#235000
0)
b1010010110 ,
b10110 -
b10010111110000111100000000000000 "
b10010111110000111100000000000000 *
b10010111110000111100000000000000 .
1$
#240000
0$
#245000
1)
b1001011111000011110000000000000 "
b1001011111000011110000000000000 *
b1001011111000011110000000000000 .
b10111 -
b101001011 ,
1$
#250000
0$
#255000
b10100101 ,
b11000 -
b10100101111100001111000000000000 "
b10100101111100001111000000000000 *
b10100101111100001111000000000000 .
1$
#260000
0$
#265000
0)
b11010010111110000111100000000000 "
b11010010111110000111100000000000 *
b11010010111110000111100000000000 .
b11001 -
b1010010 ,
1$
#270000
0$
#275000
1)
b101001 ,
b11010 -
b1101001011111000011110000000000 "
b1101001011111000011110000000000 *
b1101001011111000011110000000000 .
1$
#280000
0$
#285000
0)
b10110100101111100001111000000000 "
b10110100101111100001111000000000 *
b10110100101111100001111000000000 .
b11011 -
b10100 ,
1$
#290000
0$
#295000
b1010 ,
b11100 -
b1011010010111110000111100000000 "
b1011010010111110000111100000000 *
b1011010010111110000111100000000 .
1$
#300000
0$
#305000
1)
b101101001011111000011110000000 "
b101101001011111000011110000000 *
b101101001011111000011110000000 .
b11101 -
b101 ,
1$
#310000
0$
#315000
0)
b10 ,
b11110 -
b10010110100101111100001111000000 "
b10010110100101111100001111000000 *
b10010110100101111100001111000000 .
1$
#320000
0$
#325000
1)
b1001011010010111110000111100000 "
b1001011010010111110000111100000 *
b1001011010010111110000111100000 .
b11111 -
b1 ,
1$
#330000
0$
#335000
0)
1!
b0 ,
b100000 -
b10100101101001011111000011110000 "
b10100101101001011111000011110000 *
b10100101101001011111000011110000 .
1$
#340000
0$
#345000
0'
1$
